neuroloft/__init__.py
neuroloft/models/__init__.py
neuroloft/models/efficientnet.py
neuroloft/models/googlenet.py
neuroloft/models/inception.py
neuroloft/models/mobilenet.py
neuroloft/models/resnet.py
neuroloft/models/vgg.py
neuroloft/utils/__init__.py
neuroloft/utils/helper_funtions.py
neuroloft-0.1.0.dist-info/METADATA
neuroloft-0.1.0.dist-info/WHEEL
neuroloft-0.1.0.dist-info/top_level.txt
neuroloft-0.1.0.dist-info/RECORD
