Metadata-Version: 2.4
Name: neuroloft
Version: 0.1.0
Summary: Predefined AI models & helper funtions
Author-email: HimaManiKanta <himachinna5415@gmail.com>
Requires-Python: >=3.12
Requires-Dist: torch>=2.8.0
Requires-Dist: torchvision>=0.23.0
Requires-Dist: numpy>=2.3.2
Requires-Dist: pandas>=2.3.2
Requires-Dist: requests>=2.32.5
Requires-Dist: matplotlib>=3.10.5
Requires-Dist: tensorflow==2.20.0
Requires-Dist: keras==3.11.3
